{
    "steps": [
        {
            "id": "start",
            "name": "start",
            "description": null
        },
        {
            "id": "setup-install-server",
            "name": "Setup: Install server",
            "description": null
        },
        {
            "id": "pages-create-yaml-page",
            "name": "Pages: Create YAML page",
            "description": null
        },
        {
            "id": "pages-install-annotations",
            "name": "Pages: Install annotations",
            "description": null
        },
        {
            "id": "pages-convert-route-to-annotation",
            "name": "Pages: Convert route to annotation",
            "description": null
        },
        {
            "id": "pages-add-show-page-hardcoded",
            "name": "Pages: Add show page hardcoded",
            "description": null
        },
        {
            "id": "pages-use-a-wildcard-route",
            "name": "Pages: Use a wildcard route",
            "description": null
        },
        {
            "id": "recipes-install-sec-checker",
            "name": "Recipes: Install sec-checker",
            "description": null
        },
        {
            "id": "twig-install-twig",
            "name": "Twig: Install twig",
            "description": null
        },
        {
            "id": "twig-render-template",
            "name": "Twig: Render template",
            "description": null
        },
        {
            "id": "twig-loop-over-comments",
            "name": "Twig: Loop over comments",
            "description": null
        },
        {
            "id": "twig-use-length-filter",
            "name": "Twig: Use length filter",
            "description": null
        },
        {
            "id": "twig-extends-but-no-block",
            "name": "Twig: Extends but no block",
            "description": null
        },
        {
            "id": "twig-add-body-block",
            "name": "Twig: Add body block",
            "description": null
        },
        {
            "id": "twig-add-title-block",
            "name": "Twig: Add title block",
            "description": null
        },
        {
            "id": "profiler-install-profiler",
            "name": "Profiler: Install profiler",
            "description": null
        },
        {
            "id": "profiler-use-dump",
            "name": "Profiler: Use dump()",
            "description": null
        },
        {
            "id": "profiler-dump-in-twig",
            "name": "Profiler: dump() in Twig",
            "description": null
        },
        {
            "id": "profiler-install-debug",
            "name": "Profiler: Install debug",
            "description": null
        },
        {
            "id": "profiler-remove-dump",
            "name": "Profiler: Remove dump()",
            "description": null
        },
        {
            "id": "profiler-unpack-debug",
            "name": "Profiler: Unpack debug",
            "description": null
        },
        {
            "id": "assets-copy-in-layout",
            "name": "Assets: Copy in layout",
            "description": null
        },
        {
            "id": "assets-copy-assets-to-public",
            "name": "Assets: Copy assets to public",
            "description": null
        },
        {
            "id": "assets-add-2-css-link-tags",
            "name": "Assets: Add 2 CSS link tags",
            "description": null
        },
        {
            "id": "assets-install-use-asset-function",
            "name": "Assets: Install & use asset function",
            "description": null
        },
        {
            "id": "assets-copy-in-article-template",
            "name": "Assets: Copy in article template",
            "description": null
        },
        {
            "id": "assets-make-template-dynamic",
            "name": "Assets: Make template dynamic",
            "description": null
        },
        {
            "id": "links-generate-homepage-link",
            "name": "Links: Generate homepage link",
            "description": null
        },
        {
            "id": "links-use-explicit-route-name",
            "name": "Links: Use explicit route name",
            "description": null
        },
        {
            "id": "links-add-homepage-template",
            "name": "Links: Add homepage template",
            "description": null
        },
        {
            "id": "links-try-to-link-to-show-page",
            "name": "Links: Try to link to show page",
            "description": null
        },
        {
            "id": "links-add-slug-parameter",
            "name": "Links: Add slug parameter",
            "description": null
        },
        {
            "id": "javascript-create-basic-js-like-behavior",
            "name": "JavaScript: Create basic JS like behavior",
            "description": null
        },
        {
            "id": "javascript-add-parent-call",
            "name": "JavaScript: Add parent() call",
            "description": null
        },
        {
            "id": "javascript-add-api-endpoint",
            "name": "JavaScript: Add API endpoint",
            "description": null
        },
        {
            "id": "javascript-make-route-post-only",
            "name": "JavaScript: Make route POST only",
            "description": null
        },
        {
            "id": "javascript-hook-up-ajax",
            "name": "JavaScript: Hook up AJAX",
            "description": null
        },
        {
            "id": "services-log-something",
            "name": "Services: Log something",
            "description": null
        },
        {
            "id": "services-show-direct-twig-usage",
            "name": "Services: Show direct Twig usage",
            "description": null
        },
        {
            "id": "services-back-to-easy-twig-render",
            "name": "Services: Back to easy Twig render",
            "description": null
        },
        {
            "id": "pre-ep2-upgrade-all-deps",
            "name": "PRE_EP2: Upgrade all deps",
            "description": null
        },
        {
            "id": "pre-ep2-clean-tutorial",
            "name": "PRE_EP2: Clean tutorial\/",
            "description": null
        },
        {
            "id": "pre-ep2-update-framework-recipe",
            "name": "PRE_EP2: Update framework recipe",
            "description": null
        },
        {
            "id": "bundle-add-some-markdown-content",
            "name": "Bundle: Add some markdown content",
            "description": null
        },
        {
            "id": "bundle-install-markdownbundle",
            "name": "Bundle: Install MarkdownBundle",
            "description": null
        },
        {
            "id": "bundle-use-the-markdown-service",
            "name": "Bundle: Use the markdown service",
            "description": null
        },
        {
            "id": "bundle-use-raw-filter",
            "name": "Bundle: Use raw filter",
            "description": null
        },
        {
            "id": "caching-cache-the-markdown-transformation",
            "name": "Caching: cache the markdown transformation",
            "description": null
        },
        {
            "id": "caching-tweak-contents",
            "name": "Caching: Tweak contents",
            "description": null
        },
        {
            "id": "config-dump-markdown",
            "name": "Config: Dump markdown",
            "description": null
        },
        {
            "id": "config-change-markdown-config",
            "name": "Config: Change markdown config",
            "description": null
        },
        {
            "id": "config-empty-step",
            "name": "Config: EMPTY STEP",
            "description": null
        },
        {
            "id": "config-dump-cache",
            "name": "Config: dump($cache)",
            "description": null
        },
        {
            "id": "config-change-to-apcu-cache",
            "name": "Config: Change to apcu cache",
            "description": null
        },
        {
            "id": "environment-tweak-twig-template",
            "name": "Environment: Tweak Twig template",
            "description": null
        },
        {
            "id": "environment-filesystem-cache-in-dev",
            "name": "Environment: Filesystem cache in dev",
            "description": null
        },
        {
            "id": "environment-remove-dump",
            "name": "Environment: Remove dump",
            "description": null
        },
        {
            "id": "services-create-markdownhelper",
            "name": "Services: Create MarkdownHelper",
            "description": null
        },
        {
            "id": "services-pass-args-to-method",
            "name": "Services: Pass args to method",
            "description": null
        },
        {
            "id": "services-use-constructor-injection",
            "name": "Services: Use constructor injection",
            "description": null
        },
        {
            "id": "custom-di-di-normal-logger",
            "name": "Custom DI: DI normal Logger",
            "description": null
        },
        {
            "id": "custom-di-custom-logger-channel",
            "name": "Custom DI: Custom logger channel",
            "description": null
        },
        {
            "id": "custom-di-configure-logger-arg",
            "name": "Custom DI: Configure $logger arg",
            "description": null
        },
        {
            "id": "custom-di-add-missing-to-arg",
            "name": "Custom DI: Add missing @ to arg",
            "description": null
        },
        {
            "id": "custom-di-use-bind-under-defaults",
            "name": "Custom DI: Use bind under _defaults",
            "description": null
        },
        {
            "id": "parameters-set-cache-adapter-parameter",
            "name": "Parameters: Set cache_adapter parameter",
            "description": null
        },
        {
            "id": "parameters-move-to-services-yaml",
            "name": "Parameters: Move to services.yaml",
            "description": null
        },
        {
            "id": "parameters-create-services-dev-yaml",
            "name": "Parameters: Create services_dev.yaml",
            "description": null
        },
        {
            "id": "parameters-try-to-inject-isdebug",
            "name": "Parameters: Try to inject $isDebug",
            "description": null
        },
        {
            "id": "parameters-bind-isdebug",
            "name": "Parameters: Bind $isDebug",
            "description": null
        },
        {
            "id": "parameters-using-kernel-debug",
            "name": "Parameters: Using %kernel.debug%",
            "description": null
        },
        {
            "id": "controller-di-try-to-use-isdebug-arg",
            "name": "Controller DI: Try to use $isDebug arg",
            "description": null
        },
        {
            "id": "controller-di-adding-constructor",
            "name": "Controller DI: adding constructor",
            "description": null
        },
        {
            "id": "controller-di-adding-comments",
            "name": "Controller DI: Adding comments",
            "description": null
        },
        {
            "id": "autowire-alias-install-slackbundle",
            "name": "Autowire Alias: Install SlackBundle",
            "description": null
        },
        {
            "id": "autowire-alias-configure-slack-endpoint",
            "name": "Autowire Alias: Configure Slack endpoint",
            "description": null
        },
        {
            "id": "autowire-alias-try-to-autowire",
            "name": "Autowire Alias: Try to autowire",
            "description": null
        },
        {
            "id": "autowire-alias-try-the-constructor",
            "name": "Autowire Alias: Try the constructor",
            "description": null
        },
        {
            "id": "autowire-alias-by-type-bind-for-slack-client",
            "name": "Autowire Alias: By-type bind for Slack client",
            "description": null
        },
        {
            "id": "autowire-alias-change-to-an-alias",
            "name": "Autowire Alias: Change to an alias",
            "description": null
        },
        {
            "id": "env-vars-move-endpoint-to-env",
            "name": "Env Vars: Move endpoint to .env",
            "description": null
        },
        {
            "id": "env-vars-cast-to-string",
            "name": "Env Vars: Cast to string",
            "description": null
        },
        {
            "id": "setter-di-create-slackclient",
            "name": "Setter DI: Create SlackClient",
            "description": null
        },
        {
            "id": "setter-di-adding-setlogger",
            "name": "Setter DI: Adding setLogger",
            "description": null
        },
        {
            "id": "setter-di-adding-required",
            "name": "Setter DI: Adding @required",
            "description": null
        },
        {
            "id": "setter-di-adding-loggertrait",
            "name": "Setter DI: Adding LoggerTrait",
            "description": null
        },
        {
            "id": "maker-install-maker",
            "name": "Maker: Install maker",
            "description": null
        },
        {
            "id": "maker-make-command",
            "name": "Maker: make:command",
            "description": null
        },
        {
            "id": "maker-customize-command",
            "name": "Maker: Customize command",
            "description": null
        },
        {
            "id": "maker-use-table-to-be-prettier",
            "name": "Maker: Use table to be prettier",
            "description": null
        },
        {
            "id": "pre-ep3-update-deps",
            "name": "PRE_EP3: Update deps",
            "description": null
        },
        {
            "id": "install-require-doctrine",
            "name": "Install: Require doctrine",
            "description": null
        },
        {
            "id": "install-customize-env-dist",
            "name": "Install: Customize .env.dist",
            "description": null
        },
        {
            "id": "entity-generate-article-entity",
            "name": "Entity: Generate Article entity",
            "description": null
        },
        {
            "id": "entity-generate-migration",
            "name": "Entity: Generate Migration",
            "description": null
        },
        {
            "id": "entity-make-slug-unique",
            "name": "Entity: Make slug unique",
            "description": null
        },
        {
            "id": "save-entity-create-admincontroller",
            "name": "Save Entity: Create AdminController",
            "description": null
        },
        {
            "id": "save-entity-create-article-object",
            "name": "Save Entity: Create Article object",
            "description": null
        },
        {
            "id": "save-entity-persist-flush",
            "name": "Save Entity: persist & flush",
            "description": null
        },
        {
            "id": "query-use-em-to-get-repo-find",
            "name": "Query: Use EM to get repo & find",
            "description": null
        },
        {
            "id": "query-pass-article-to-template",
            "name": "Query: Pass article to template",
            "description": null
        },
        {
            "id": "twigextension-make-twig-extension",
            "name": "TwigExtension: make:twig-extension",
            "description": null
        },
        {
            "id": "twigextension-add-cached-markdown-filter",
            "name": "TwigExtension: Add cached_markdown filter",
            "description": null
        },
        {
            "id": "twigextension-process-through-markdown",
            "name": "TwigExtension: Process through markdown",
            "description": null
        },
        {
            "id": "twigextension-print-publishedat",
            "name": "TwigExtension: Print publishedAt",
            "description": null
        },
        {
            "id": "twigextension-install-knptimebundle",
            "name": "TwigExtension: Install KnpTimeBundle",
            "description": null
        },
        {
            "id": "twigextension-use-ago-filter",
            "name": "TwigExtension: Use ago filter",
            "description": null
        },
        {
            "id": "more-queries-use-repo-in-list",
            "name": "More Queries: Use repo in list",
            "description": null
        },
        {
            "id": "more-queries-change-order",
            "name": "More Queries: Change order",
            "description": null
        },
        {
            "id": "more-queries-uncomment-repo-method",
            "name": "More Queries: Uncomment repo method",
            "description": null
        },
        {
            "id": "more-queries-write-query-builder-query",
            "name": "More Queries: Write query builder query",
            "description": null
        },
        {
            "id": "more-queries-autowire-articlerepository",
            "name": "More Queries: Autowire ArticleRepository",
            "description": null
        },
        {
            "id": "more-queries-use-param-converter",
            "name": "More Queries: Use param converter",
            "description": null
        },
        {
            "id": "updates-generate-a-few-more-fields",
            "name": "Updates: Generate a few more fields",
            "description": null
        },
        {
            "id": "updates-default-starcount-to-0",
            "name": "Updates: Default starCount to 0",
            "description": null
        },
        {
            "id": "updates-set-new-fields-in-dummy-page",
            "name": "Updates: Set new fields in dummy page",
            "description": null
        },
        {
            "id": "updates-render-in-templates",
            "name": "Updates: Render in templates",
            "description": null
        },
        {
            "id": "updates-custom-imagepath-method",
            "name": "Updates: Custom imagePath method",
            "description": null
        },
        {
            "id": "updates-make-heart-endpoint-real",
            "name": "Updates: Make heart endpoint real",
            "description": null
        },
        {
            "id": "updates-smart-method-incrementheartcount",
            "name": "Updates: Smart method: incrementHeartCount()",
            "description": null
        },
        {
            "id": "fixtures-install-fixtures-bundle",
            "name": "Fixtures: Install fixtures bundle",
            "description": null
        },
        {
            "id": "fixtures-generate-fixture",
            "name": "Fixtures: Generate fixture",
            "description": null
        },
        {
            "id": "fixtures-copy-fixtures-into-code",
            "name": "Fixtures: Copy fixtures into code",
            "description": null
        },
        {
            "id": "fixtures-create-basefixture",
            "name": "Fixtures: Create BaseFixture",
            "description": null
        },
        {
            "id": "fixtures-add-createmany-method",
            "name": "Fixtures: Add createMany() method",
            "description": null
        },
        {
            "id": "fixtures-empty-step",
            "name": "Fixtures: EMPTY STEP",
            "description": null
        },
        {
            "id": "fixtures-install-faker",
            "name": "Fixtures: Install faker",
            "description": null
        },
        {
            "id": "fixtures-use-faker-in-a-few-place",
            "name": "Fixtures: Use faker in a few place",
            "description": null
        },
        {
            "id": "fixtures-use-random-title",
            "name": "Fixtures: Use random title",
            "description": null
        },
        {
            "id": "extensions-install-stofdoctrine",
            "name": "Extensions: Install StofDoctrine",
            "description": null
        },
        {
            "id": "extensions-use-sluggable",
            "name": "Extensions: Use Sluggable",
            "description": null
        },
        {
            "id": "extensions-add-createdat-updatedat",
            "name": "Extensions: Add createdAt\/updatedAt",
            "description": null
        },
        {
            "id": "extensions-add-timestampable",
            "name": "Extensions: add Timestampable",
            "description": null
        },
        {
            "id": "extensions-add-timestampabletrait",
            "name": "Extensions: Add TimestampableTrait",
            "description": null
        }
    ],
    "sha": "e0f427e184a8468e89b427219aea8c1dff586353"
}